{
  "applications": "*",
  "changelogDate": "20230509150146",
  "dto": "no",
  "embedded": false,
  "entityTableName": "company",
  "fields": [
    {
      "fieldName": "companyName",
      "fieldType": "String",
      "fieldValidateRules": ["required"]
    }
  ],
  "fluentMethods": true,
  "jpaMetamodelFiltering": false,
  "name": "Company",
  "pagination": "no",
  "readOnly": false,
  "relationships": [
    {
      "otherEntityName": "customer",
      "otherEntityRelationshipName": "company",
      "relationshipName": "customer",
      "relationshipType": "one-to-many"
    }
  ],
  "service": "no"
}
